{
  "inherits": "kaolin-dark",
  "keyword.directive": "selection0",
  "special": "ultramarine1",
  "variable.other.member": {"fg": "constant", "modifiers": ["italic"]},
  "variable": "ultramarine1",
  "variable.parameter": "constant",
  "type.builtin": "selection0",
  "function": {"fg": "selection0"},
  "function.builtin": "ultramarine1",
  "tag": {"fg": "hint", "modifiers": ["italic"]},
  "constant.builtin": {"fg": "selection0"},
  "string": "green0",
  "constant.numeric": "selection0",
  "module": "selection0",
  "ui.linenr.selected": {"fg": "green1", "modifiers": ["bold"]},
  "ui.statusline": {"fg": "selection0", "bg": "bg1"},
  "ui.statusline.normal": {"fg": "hint", "bg": "bg1", "modifiers": ["bold"]},
  "ui.statusline.insert": {"fg": "warn", "bg": "bg1", "modifiers": ["reversed", "bold"]},
  "ui.statusline.select": {"fg": "constant", "bg": "bg1", "modifiers": ["reversed", "bold"]},
  "ui.text": {"fg": "fg0"},
  "ui.text.focus": {"fg": "green1", "modifiers": ["bold"]},
  "ui.cursor.match": {"fg": "fg1", "bg": "gray0"},
  "ui.menu.selected": {"fg": "green1", "bg": "bg2", "modifiers": ["bold"]},
  "ui.virtual.wrap": "fg1",
  "ui.virtual.indent-guide": "fg1",
  "ui.virtual.inlay-hint": "gray0",
  "ui.virtual.inlay-hint.parameter": {"fg": "gray0", "modifiers": ["italic"]},
  "ui.virtual.inlay-hint.type": {"fg": "gray0", "modifiers": ["italic"]},
  "markup.heading": {"fg": "ultramarine1", "modifiers": ["bold"]},
  "markup.link.url": {"fg": "info", "underline": {"style": "line"}},
  "markup.link.text": "info",
  "markup.raw": "constant",
  "palette" :
    {
      "bg0": "#edeeeb",
      "bg1": "#dfe1dc",
      "bg2": "#d1d4cd",
      "fg0": "#383e3f",
      "fg1": "#bebec4",
      "gray0": "#7c878a",
      "green0": "#39854c",
      "green1": "#18a318",
      "selection0": "#4c7a90",
      "selection1": "#d3e4f0",
      "type": "#e36b3f",
      "hint": "#13665f",
      "info": "#3b84cc",
      "warn": "#dbac66",
      "error": "#e84c58",
      "constant": "#845A84",
      "ultramarine1": "#6d46e3"
    }
}
